carpedm/__init__.py
carpedm/data/HiraginoMaruGothic.ttc
carpedm/data/__init__.py
carpedm/data/download.py
carpedm/data/io.py
carpedm/data/lang.py
carpedm/data/meta.py
carpedm/data/ops.py
carpedm/data/preproc.py
carpedm/data/providers.py
carpedm/data/stats.py
carpedm/data/util.py
carpedm/data/viewer.py
carpedm/data/small/__init__.py
carpedm/data/small/200003076/200003076_coordinate.csv
carpedm/data/small/200003076/images/200003076_00005_1.jpg
carpedm/data/small/200003967/200003967_coordinate.csv
carpedm/data/small/200003967/images/200003967_00007_2.jpg
carpedm/data/small/200014740/200014740_coordinate.csv
carpedm/data/small/200014740/images/200014740-00004_1.jpg
carpedm/data/small/200021637/200021637_coordinate.csv
carpedm/data/small/200021637/images/200021637-00005_2.jpg
carpedm/data/small/200021660/200021660_coordinate.csv
carpedm/data/small/200021660/images/200021660-00005_1.jpg
carpedm/data/small/200021712/200021712_coordinate.csv
carpedm/data/small/200021712/images/200021712-00004_2.jpg
carpedm/data/small/200021763/200021763_coordinate.csv
carpedm/data/small/200021763/images/200021763-00004_2.jpg
carpedm/data/small/200021802/200021802_coordinate.csv
carpedm/data/small/200021802/images/200021802-00005_1.jpg
carpedm/data/small/200021851/200021851_coordinate.csv
carpedm/data/small/200021851/images/200021851_00007_2.jpg
carpedm/data/small/200021853/200021853_coordinate.csv
carpedm/data/small/200021853/images/200021853-00005_1.jpg
carpedm/data/small/200021869/200021869_coordinate.csv
carpedm/data/small/200021869/images/200021869-00004_2.jpg
carpedm/data/small/200021925/200021925_coordinate.csv
carpedm/data/small/200021925/images/200021925-00013_1.jpg
carpedm/data/small/200022050/200022050_coordinate.csv
carpedm/data/small/200022050/images/200022050-00007_1.jpg
carpedm/data/small/__pycache__/__init__.cpython-36.pyc
carpedm/data/small/brsk00000/brsk00000_coordinate.csv
carpedm/data/small/brsk00000/images/brsk001-009.jpg
carpedm-0.1.7.dist-info/METADATA
carpedm-0.1.7.dist-info/RECORD
carpedm-0.1.7.dist-info/WHEEL
carpedm-0.1.7.dist-info/entry_points.txt
carpedm-0.1.7.dist-info/top_level.txt
