Metadata-Version: 2.1
Name: carpedm
Version: 0.1.7
Summary: Character shapes image metadata manager for machine learning.
Home-page: http://github.com/SimulatedANeal/carpedm
Author: Neal Digre
Author-email: nealdigre@ed-alumni.net
License: MIT
Keywords: machine learning framework deep learning image-to-text japanese character
Platform: UNKNOWN
Classifier: Development Status :: 3 - Alpha
Classifier: License :: OSI Approved :: MIT License
Classifier: Intended Audience :: Science/Research
Classifier: Topic :: Scientific/Engineering
Classifier: Programming Language :: Python :: 3
Classifier: Programming Language :: Python :: 3.4
Classifier: Programming Language :: Python :: 3.5
Classifier: Programming Language :: Python :: 3.6
Classifier: Programming Language :: Python :: 3.7
Requires-Python: ~=3.4
Provides-Extra: plot
Provides-Extra: tfgpu
Provides-Extra: tf
Provides-Extra: docs
Requires-Dist: numpy (>=1.14)
Requires-Dist: tensorflow (>=1.5)
Requires-Dist: Pillow (>=5.1)
Provides-Extra: docs
Requires-Dist: sphinx (>=1.7); extra == 'docs'
Requires-Dist: sphinx-rtd-theme; extra == 'docs'
Provides-Extra: plot
Requires-Dist: matplotlib (>=2.1.2); extra == 'plot'
Provides-Extra: tf
Requires-Dist: tensorflow (>=1.5); extra == 'tf'
Provides-Extra: tfgpu
Requires-Dist: tensorflow-gpu (>1.5); extra == 'tfgpu'
